net_franky/__init__.py
net_franky/cb_robot.py
net_franky/setup.py
net_franky/tools.py
net_franky/franky/__init__.py
net_franky/franky/__init__.pyi
net_franky/franky/_franky.pyi
net_franky/franky/motion.pyi
net_franky/franky/reaction.pyi
net_franky/franky/robot.pyi
net_franky/franky/robot_web_session.pyi
net_franky-1.0.0.dist-info/licenses/LICENSE.md
net_franky-1.0.0.dist-info/METADATA
net_franky-1.0.0.dist-info/WHEEL
net_franky-1.0.0.dist-info/top_level.txt
net_franky-1.0.0.dist-info/RECORD
