Metadata-Version: 2.4
Name: net_franky
Version: 1.0.0
Summary: Minimal pyproject for the net_franky package
Author: Yannik Blei
License-File: LICENSE.md
Requires-Dist: scipy
Requires-Dist: rpyc==6.0.2
Provides-Extra: server
Requires-Dist: franky-control; extra == "server"
Dynamic: license-file
